{
  "comments": [
    {
      "id": "80",
      "commentList": []
    },
    {
      "id": "81",
      "commentList": []
    },
    {
      "id": "82",
      "commentList": []
    },
    {
      "id": "83",
      "commentList": []
    },
    {
      "id": "84",
      "commentList": []
    },
    {
      "id": "85",
      "commentList": []
    },
    {
      "id": "86",
      "commentList": []
    },
    {
      "id": "87",
      "commentList": []
    },
    {
      "id": "88",
      "commentList": []
    },
    {
      "id": "89",
      "commentList": []
    },
    {
      "id": "90",
      "commentList": []
    },
    {
      "id": "91",
      "commentList": []
    },
    {
      "id": "92",
      "commentList": []
    },
    {
      "id": "93",
      "commentList": []
    },
    {
      "id": "94",
      "commentList": []
    },
    {
      "id": "95",
      "commentList": []
    },
    {
      "id": "96",
      "commentList": []
    },
    {
      "id": "97",
      "commentList": []
    },
    {
      "id": "98",
      "commentList": []
    },
    {
      "id": "99",
      "commentList": []
    },
    {
      "id": "100",
      "commentList": []
    },
    {
      "id": "101",
      "commentList": []
    },
    {
      "id": "102",
      "commentList": []
    },
    {
      "id": "103",
      "commentList": []
    },
    {
      "id": "104",
      "commentList": [
       
      ]
    },
    {
      "id": "105",
      "commentList": []
    },
    {
      "id": "106",
      "commentList": []
    },
    {
      "id": "107",
      "commentList": []
    },
    {
      "id": "108",
      "commentList": [
        {
          "name": "Martin",
          "comment": "It works!"
        }
      ]
    },
    {
      "id": "109",
      "commentList": []
    }
  ]
}